django_userpack/__init__.py
django_userpack/admin.py
django_userpack/apps.py
django_userpack/models.py
django_userpack/tests.py
django_userpack/views.py
django_userpack/migrations/__init__.py
django_userpack-0.2.0.dist-info/licenses/LICENSE
django_userpack-0.2.0.dist-info/METADATA
django_userpack-0.2.0.dist-info/WHEEL
django_userpack-0.2.0.dist-info/top_level.txt
django_userpack-0.2.0.dist-info/RECORD
