Metadata-Version: 2.4
Name: django_userpack
Version: 0.2.0
Summary: A powerful and extendable Django user system with advanced fields, admin, and authentication features.
Author: AboalfazlH
License: MIT
Project-URL: Homepage, https://github.com/aboalfazlH/django_userpack
Project-URL: Repository, https://github.com/aboalfazl/django_userpack
Project-URL: Documentation, https://pypi.org/project/django_userpack/
Keywords: django,auth,user,custom user model,django user,django userpack
Requires-Python: >=3.9
License-File: LICENSE
Requires-Dist: django>=4.2
Requires-Dist: Pillow>=9.0
Dynamic: license-file
